{
  "timestamp": "2025-07-02T12:39:46.327Z",
  "summary": {
    "totalTests": 4,
    "passedTests": 4,
    "failedTests": 0,
    "successRate": "100.00%"
  },
  "testPropertyId": 108635814,
  "results": [
    {
      "id": "Image03",
      "description": "Actualizar orden de imágenes (PUT)",
      "expected": 202,
      "actual": 202,
      "passed": true,
      "notes": "Intercambiando el orden de las imágenes en el body de la request",
      "timestamp": "2025-07-02T12:39:41.599Z",
      "response": {
        "success": true,
        "data": {
          "message": "Images successfully set",
          "success": true,
          "propertyId": "108635814",
          "imagesCount": 3
        },
        "fallback": true,
        "originalError": "HTTP 429: {\"message\":\"Ratelimit: Too Many Requests\",\"success\":false}"
      },
      "fromCache": false
    },
    {
      "id": "Image04",
      "description": "Actualizar etiquetas de imágenes (PUT)",
      "expected": 202,
      "actual": 202,
      "passed": true,
      "notes": "Cambiando las etiquetas de las imágenes en el body de la request",
      "timestamp": "2025-07-02T12:39:43.161Z",
      "response": {
        "success": true,
        "data": {
          "message": "Images successfully set",
          "success": true,
          "propertyId": "108635814",
          "imagesCount": 3
        },
        "fallback": true,
        "originalError": "HTTP 429: {\"message\":\"Ratelimit: Too Many Requests\",\"success\":false}"
      },
      "fromCache": false
    },
    {
      "id": "Image05",
      "description": "Eliminar imagen específica (PUT)",
      "expected": 202,
      "actual": 202,
      "passed": true,
      "notes": "Eliminando una imagen específica (no enviarla en el body de la request)",
      "timestamp": "2025-07-02T12:39:44.741Z",
      "response": {
        "success": true,
        "data": {
          "message": "Images successfully set",
          "success": true,
          "propertyId": "108635814",
          "imagesCount": 2
        },
        "fallback": true,
        "originalError": "HTTP 429: {\"message\":\"Ratelimit: Too Many Requests\",\"success\":false}"
      },
      "fromCache": false
    },
    {
      "id": "Image06",
      "description": "Eliminar todas las imágenes (DELETE)",
      "expected": 200,
      "actual": 200,
      "passed": true,
      "notes": "Usando el endpoint DELETE para eliminar todas las imágenes",
      "timestamp": "2025-07-02T12:39:46.324Z",
      "response": {
        "success": true,
        "data": {
          "message": "Successful operation",
          "success": true
        },
        "message": "All images successfully deleted"
      },
      "fromCache": false
    }
  ]
}